moconut/__init__.py
moconut/maps.py
moconut-0.0.3.dist-info/LICENSE
moconut-0.0.3.dist-info/METADATA
moconut-0.0.3.dist-info/WHEEL
moconut-0.0.3.dist-info/top_level.txt
moconut-0.0.3.dist-info/RECORD
