Metadata-Version: 2.1
Name: moconut
Version: 0.0.3
Summary: Model Construction Utils
Author-email: Danzel Serrano <danzel.serrano@gmail.com>
Project-URL: Homepage, https://github.com/dependanz/moconut
Classifier: Programming Language :: Python :: 3
Classifier: License :: OSI Approved :: MIT License
Classifier: Operating System :: OS Independent
Requires-Python: >=3.10
License-File: LICENSE
Requires-Dist: torch
